{
    {
        "username": "joolscustomer",
        "email": "jools@email.com",
        "password": "password1"
    },
    {
        "username": "doratablet",
        "email": "dora@email.com",
        "password": "password2"
    },
    {
        "username": "fisherfox",
        "email": "fisher@email.com",
        "password": "password3"
    },
    {
        "username": "rylandengine",
        "email": "ryland@email.com",
        "password": "password4"
    },
    {
        "username": "heathbulb",
        "email": "heath@email.com",
        "password": "password5"
    }
}